pointr_cloud_common/__init__.py
pointr_cloud_common/api/__init__.py
pointr_cloud_common/api/mapscale_token_service.py
pointr_cloud_common/api/mapscale_v9_service.py
pointr_cloud_common/api/common/__init__.py
pointr_cloud_common/api/v8/__init__.py
pointr_cloud_common/api/v8/base_service.py
pointr_cloud_common/api/v8/building_service.py
pointr_cloud_common/api/v8/client_service.py
pointr_cloud_common/api/v8/environment_token_service.py
pointr_cloud_common/api/v8/errors.py
pointr_cloud_common/api/v8/feature_service.py
pointr_cloud_common/api/v8/level_service.py
pointr_cloud_common/api/v8/poi_service.py
pointr_cloud_common/api/v8/sdk_service.py
pointr_cloud_common/api/v8/site_service.py
pointr_cloud_common/api/v8/v8_api_service.py
pointr_cloud_common/api/v9/__init__.py
pointr_cloud_common/api/v9/base_service.py
pointr_cloud_common/api/v9/building_service.py
pointr_cloud_common/api/v9/client_service.py
pointr_cloud_common/api/v9/environment_token_service.py
pointr_cloud_common/api/v9/feature_service.py
pointr_cloud_common/api/v9/level_service.py
pointr_cloud_common/api/v9/poi_service.py
pointr_cloud_common/api/v9/sdk_service.py
pointr_cloud_common/api/v9/site_service.py
pointr_cloud_common/api/v9/v9_api_service.py
pointr_cloud_common/dto/__init__.py
pointr_cloud_common/dto/common/__init__.py
pointr_cloud_common/dto/v8/__init__.py
pointr_cloud_common/dto/v9/__init__.py
pointr_cloud_common/dto/v9/base_dto.py
pointr_cloud_common/dto/v9/base_migration_dto.py
pointr_cloud_common/dto/v9/building_dto.py
pointr_cloud_common/dto/v9/building_dtos.py
pointr_cloud_common/dto/v9/building_migration_dto.py
pointr_cloud_common/dto/v9/client_dto.py
pointr_cloud_common/dto/v9/client_dtos.py
pointr_cloud_common/dto/v9/client_metadata_dto.py
pointr_cloud_common/dto/v9/client_migration_dto.py
pointr_cloud_common/dto/v9/create_response_dto.py
pointr_cloud_common/dto/v9/gps_geofence_dto.py
pointr_cloud_common/dto/v9/level_dto.py
pointr_cloud_common/dto/v9/level_dtos.py
pointr_cloud_common-0.1.32.dist-info/licenses/LICENSE-PROPRIETARY.md
pointr_cloud_common-0.1.32.dist-info/METADATA
pointr_cloud_common-0.1.32.dist-info/WHEEL
pointr_cloud_common-0.1.32.dist-info/top_level.txt
pointr_cloud_common-0.1.32.dist-info/RECORD
