Metadata-Version: 2.4
Name: pointr-cloud-common
Version: 0.1.32
Summary: Common utilities and DTOs shared across PointrCloud apps
Author-email: Serhat Gürgenyatağı <serhat.gurgenyatagi@pointr.tech>
License: # PROPRIETARY SOFTWARE LICENSE
Project-URL: Homepage, https://github.com/pointrlabs/ptr-swdel-internal-util-automation/tree/develop/PointrCloudCommon
Project-URL: Bug Tracker, https://github.com/pointrlabs/ptr-swdel-internal-util-automation/issues
Classifier: Programming Language :: Python :: 3
Classifier: Programming Language :: Python :: 3.9
Classifier: Programming Language :: Python :: 3.10
Classifier: License :: Other/Proprietary License
Classifier: Operating System :: OS Independent
Classifier: Intended Audience :: Developers
Classifier: Development Status :: 4 - Beta
Classifier: Topic :: Software Development :: Libraries
Requires-Python: >=3.9
License-File: LICENSE-PROPRIETARY.md
Requires-Dist: requests>=2.25.0
Requires-Dist: smartsheet-python-sdk
Requires-Dist: pandas
Requires-Dist: sqlalchemy>=1.4.0
Requires-Dist: retrying>=1.3.3
Requires-Dist: mysql-connector-python>=8.0.0
Requires-Dist: pyodbc>=4.0.30
Requires-Dist: python-dotenv>=0.19.0
Requires-Dist: streamlit>=1.0.0
Requires-Dist: GitPython>=3.1.0
Provides-Extra: database
Requires-Dist: sqlalchemy>=1.4.0; extra == "database"
Requires-Dist: mysql-connector-python>=8.0.0; extra == "database"
Requires-Dist: pyodbc>=4.0.30; extra == "database"
Provides-Extra: web
Requires-Dist: streamlit>=1.0.0; extra == "web"
Provides-Extra: git
Requires-Dist: GitPython>=3.1.0; extra == "git"
Provides-Extra: jira
Requires-Dist: python-dotenv>=0.19.0; extra == "jira"
Provides-Extra: retry
Requires-Dist: retrying>=1.3.3; extra == "retry"
Provides-Extra: dev
Requires-Dist: pytest>=6.0.0; extra == "dev"
Requires-Dist: pytest-cov>=2.0.0; extra == "dev"
Requires-Dist: black>=21.0.0; extra == "dev"
Requires-Dist: flake8>=3.8.0; extra == "dev"
Requires-Dist: mypy>=0.812; extra == "dev"
Provides-Extra: all
Requires-Dist: sqlalchemy>=1.4.0; extra == "all"
Requires-Dist: mysql-connector-python>=8.0.0; extra == "all"
Requires-Dist: pyodbc>=4.0.30; extra == "all"
Requires-Dist: streamlit>=1.0.0; extra == "all"
Requires-Dist: GitPython>=3.1.0; extra == "all"
Requires-Dist: python-dotenv>=0.19.0; extra == "all"
Requires-Dist: retrying>=1.3.3; extra == "all"
Dynamic: license-file
